utoolc/__init__.py
utoolc/do.py
utoolc/get_random.py
utoolc/easy/__init__.py
utoolc/easy/easy_say.py
utoolc/utils/__init__.py
utoolc/utils/print_msg_to_log_model.py
utoolc/utils/start_to_end_time_consuming.py
utoolc/utils/utils.py
utoolc-0.1.3.dist-info/METADATA
utoolc-0.1.3.dist-info/WHEEL
utoolc-0.1.3.dist-info/top_level.txt
utoolc-0.1.3.dist-info/RECORD
