Metadata-Version: 2.1
Name: utoolc
Version: 0.1.3
Summary: ❤PyJustToolc(utoolc) > Python Tools For U (You)❤
Home-page: https://gitee.com/ahviplc/PyJustToolc
Author: LC
Author-email: ahlc@sina.cn
Maintainer: LC
License: LICENSE
Download-URL: https://pypi.org/project/utoolc/#files
Platform: Windows
Platform: MacOS
Platform: Linux
Classifier: Development Status :: 3 - Alpha
Classifier: Topic :: Text Processing
Classifier: License :: OSI Approved :: MIT License
Classifier: Operating System :: MacOS :: MacOS X
Classifier: Operating System :: Microsoft :: Windows
Classifier: Operating System :: POSIX
Classifier: Programming Language :: Python :: 3
Classifier: Programming Language :: Python :: 3.8
Requires-Dist: psutil (>=5.8.0)
Requires-Dist: requests (>=2.25.1)
Requires-Dist: twine (>=3.4.1)
Requires-Dist: wheel (>=0.36.2)
